vvs/__init__.py
vvs/cli.py
vvs-0.4.6.dist-info/DESCRIPTION.rst
vvs-0.4.6.dist-info/METADATA
vvs-0.4.6.dist-info/RECORD
vvs-0.4.6.dist-info/WHEEL
vvs-0.4.6.dist-info/entry_points.txt
vvs-0.4.6.dist-info/metadata.json
vvs-0.4.6.dist-info/top_level.txt
