Metadata-Version: 2.0
Name: vvs
Version: 0.4.6
Summary: Displays upcoming departure times from stations on the Stuttgart public transport network
Home-page: https://github.com/kopf/vvs
Author: Aengus Walton
Author-email: ventolin@gmail.com
License: Apache
Platform: UNKNOWN
Classifier: Development Status :: 4 - Beta
Classifier: License :: OSI Approved :: Apache Software License
Classifier: Programming Language :: Python
Classifier: Programming Language :: Python :: 2.7
Classifier: Programming Language :: Python :: 3.4
Classifier: Programming Language :: Python :: 3.5
Requires-Dist: beautifulsoup4
Requires-Dist: click
Requires-Dist: requests
Requires-Dist: pytz
